jxa_builder/__init__.py
jxa_builder/cli.py
jxa_builder/commands/__init__.py
jxa_builder/commands/_shared_options.py
jxa_builder/commands/build.py
jxa_builder/commands/freeze_nodejs_deps.py
jxa_builder/commands/install.py
jxa_builder/commands/uninstall.py
jxa_builder/core/constants.py
jxa_builder/core/get_dependency_modules.py
jxa_builder/core/get_dependency_modules_bak.py
jxa_builder/core/get_project_config.py
jxa_builder/core/manage_outputs.py
jxa_builder/core/models.py
jxa_builder/core/modify_app_internals.py
jxa_builder/utils/__init__.py
jxa_builder/utils/click_importer.py
jxa_builder/utils/logger.py
jxa_builder/utils/printit.py
jxa_builder/utils/recase.py
jxa_builder/utils/remove_empty_values.py
jxa_builder-1.0.1.dist-info/LICENSE
jxa_builder-1.0.1.dist-info/METADATA
jxa_builder-1.0.1.dist-info/WHEEL
jxa_builder-1.0.1.dist-info/entry_points.txt
jxa_builder-1.0.1.dist-info/RECORD
