Metadata-Version: 2.1
Name: jxa-builder
Version: 1.0.1
Summary: A Javascript for Automation build system
License: BSD-4-Clause
Author: Sebastian Pilarz
Requires-Python: >=3.8,<4.0
Classifier: License :: Other/Proprietary License
Classifier: Programming Language :: Python :: 3
Classifier: Programming Language :: Python :: 3.8
Classifier: Programming Language :: Python :: 3.9
Classifier: Programming Language :: Python :: 3.10
Classifier: Programming Language :: Python :: 3.11
Classifier: Programming Language :: Python :: 3.12
Requires-Dist: pydantic (>=2.5.2,<3.0.0)
Requires-Dist: rich-click (>=1.7.2,<2.0.0)
Requires-Dist: typing-extensions (>=4.8.0,<5.0.0)
